[{"code":"086402001","name":"Banahao","oldName":"","subMunicipalityCode":false,"cityCode":false,"municipalityCode":"086402000","districtCode":false,"provinceCode":"086400000","regionCode":"080000000","islandGroupCode":"visayas","psgc10DigitCode":"0806402001"},{"code":"086402002","name":"Baugo","oldName":"","subMunicipalityCode":false,"cityCode":false,"municipalityCode":"086402000","districtCode":false,"provinceCode":"086400000","regionCode":"080000000","islandGroupCode":"visayas","psgc10DigitCode":"0806402002"},{"code":"086402003","name":"Beniton","oldName":"","subMunicipalityCode":false,"cityCode":false,"municipalityCode":"086402000","districtCode":false,"provinceCode":"086400000","regionCode":"080000000","islandGroupCode":"visayas","psgc10DigitCode":"0806402003"},{"code":"086402004","name":"Buenavista","oldName":"","subMunicipalityCode":false,"cityCode":false,"municipalityCode":"086402000","districtCode":false,"provinceCode":"086400000","regionCode":"080000000","islandGroupCode":"visayas","psgc10DigitCode":"0806402004"},{"code":"086402005","name":"Bunga","oldName":"","subMunicipalityCode":false,"cityCode":false,"municipalityCode":"086402000","districtCode":false,"provinceCode":"086400000","regionCode":"080000000","islandGroupCode":"visayas","psgc10DigitCode":"0806402005"},{"code":"086402006","name":"Casao","oldName":"","subMunicipalityCode":false,"cityCode":false,"municipalityCode":"086402000","districtCode":false,"provinceCode":"086400000","regionCode":"080000000","islandGroupCode":"visayas","psgc10DigitCode":"0806402006"},{"code":"086402007","name":"Catmon","oldName":"","subMunicipalityCode":false,"cityCode":false,"municipalityCode":"086402000","districtCode":false,"provinceCode":"086400000","regionCode":"080000000","islandGroupCode":"visayas","psgc10DigitCode":"0806402007"},{"code":"086402008","name":"Catoogan","oldName":"","subMunicipalityCode":false,"cityCode":false,"municipalityCode":"086402000","districtCode":false,"provinceCode":"086400000","regionCode":"080000000","islandGroupCode":"visayas","psgc10DigitCode":"0806402008"},{"code":"086402009","name":"Cawayanan","oldName":"","subMunicipalityCode":false,"cityCode":false,"municipalityCode":"086402000","districtCode":false,"provinceCode":"086400000","regionCode":"080000000","islandGroupCode":"visayas","psgc10DigitCode":"0806402009"},{"code":"086402010","name":"Dao","oldName":"","subMunicipalityCode":false,"cityCode":false,"municipalityCode":"086402000","districtCode":false,"provinceCode":"086400000","regionCode":"080000000","islandGroupCode":"visayas","psgc10DigitCode":"0806402010"},{"code":"086402011","name":"Divisoria","oldName":"","subMunicipalityCode":false,"cityCode":false,"municipalityCode":"086402000","districtCode":false,"provinceCode":"086400000","regionCode":"080000000","islandGroupCode":"visayas","psgc10DigitCode":"0806402011"},{"code":"086402012","name":"Esperanza","oldName":"","subMunicipalityCode":false,"cityCode":false,"municipalityCode":"086402000","districtCode":false,"provinceCode":"086400000","regionCode":"080000000","islandGroupCode":"visayas","psgc10DigitCode":"0806402012"},{"code":"086402013","name":"Guinsangaan","oldName":"","subMunicipalityCode":false,"cityCode":false,"municipalityCode":"086402000","districtCode":false,"provinceCode":"086400000","regionCode":"080000000","islandGroupCode":"visayas","psgc10DigitCode":"0806402013"},{"code":"086402014","name":"Hibagwan","oldName":"","subMunicipalityCode":false,"cityCode":false,"municipalityCode":"086402000","districtCode":false,"provinceCode":"086400000","regionCode":"080000000","islandGroupCode":"visayas","psgc10DigitCode":"0806402014"},{"code":"086402015","name":"Hilaan","oldName":"","subMunicipalityCode":false,"cityCode":false,"municipalityCode":"086402000","districtCode":false,"provinceCode":"086400000","regionCode":"080000000","islandGroupCode":"visayas","psgc10DigitCode":"0806402015"},{"code":"086402016","name":"Himakilo","oldName":"","subMunicipalityCode":false,"cityCode":false,"municipalityCode":"086402000","districtCode":false,"provinceCode":"086400000","regionCode":"080000000","islandGroupCode":"visayas","psgc10DigitCode":"0806402016"},{"code":"086402017","name":"Hitawos","oldName":"","subMunicipalityCode":false,"cityCode":false,"municipalityCode":"086402000","districtCode":false,"provinceCode":"086400000","regionCode":"080000000","islandGroupCode":"visayas","psgc10DigitCode":"0806402017"},{"code":"086402018","name":"Lanao","oldName":"","subMunicipalityCode":false,"cityCode":false,"municipalityCode":"086402000","districtCode":false,"provinceCode":"086400000","regionCode":"080000000","islandGroupCode":"visayas","psgc10DigitCode":"0806402018"},{"code":"086402019","name":"Lawgawan","oldName":"","subMunicipalityCode":false,"cityCode":false,"municipalityCode":"086402000","districtCode":false,"provinceCode":"086400000","regionCode":"080000000","islandGroupCode":"visayas","psgc10DigitCode":"0806402019"},{"code":"086402020","name":"Mahayahay","oldName":"","subMunicipalityCode":false,"cityCode":false,"municipalityCode":"086402000","districtCode":false,"provinceCode":"086400000","regionCode":"080000000","islandGroupCode":"visayas","psgc10DigitCode":"0806402020"},{"code":"086402021","name":"Malbago","oldName":"","subMunicipalityCode":false,"cityCode":false,"municipalityCode":"086402000","districtCode":false,"provinceCode":"086400000","regionCode":"080000000","islandGroupCode":"visayas","psgc10DigitCode":"0806402021"},{"code":"086402022","name":"Mauylab","oldName":"","subMunicipalityCode":false,"cityCode":false,"municipalityCode":"086402000","districtCode":false,"provinceCode":"086400000","regionCode":"080000000","islandGroupCode":"visayas","psgc10DigitCode":"0806402022"},{"code":"086402023","name":"Paku","oldName":"","subMunicipalityCode":false,"cityCode":false,"municipalityCode":"086402000","districtCode":false,"provinceCode":"086400000","regionCode":"080000000","islandGroupCode":"visayas","psgc10DigitCode":"0806402023"},{"code":"086402024","name":"Pamahawan","oldName":"","subMunicipalityCode":false,"cityCode":false,"municipalityCode":"086402000","districtCode":false,"provinceCode":"086400000","regionCode":"080000000","islandGroupCode":"visayas","psgc10DigitCode":"0806402024"},{"code":"086402025","name":"Pamigsian","oldName":"","subMunicipalityCode":false,"cityCode":false,"municipalityCode":"086402000","districtCode":false,"provinceCode":"086400000","regionCode":"080000000","islandGroupCode":"visayas","psgc10DigitCode":"0806402025"},{"code":"086402026","name":"Pangi","oldName":"","subMunicipalityCode":false,"cityCode":false,"municipalityCode":"086402000","districtCode":false,"provinceCode":"086400000","regionCode":"080000000","islandGroupCode":"visayas","psgc10DigitCode":"0806402026"},{"code":"086402027","name":"Poblacion","oldName":"","subMunicipalityCode":false,"cityCode":false,"municipalityCode":"086402000","districtCode":false,"provinceCode":"086400000","regionCode":"080000000","islandGroupCode":"visayas","psgc10DigitCode":"0806402027"},{"code":"086402028","name":"Sampongon","oldName":"","subMunicipalityCode":false,"cityCode":false,"municipalityCode":"086402000","districtCode":false,"provinceCode":"086400000","regionCode":"080000000","islandGroupCode":"visayas","psgc10DigitCode":"0806402028"},{"code":"086402029","name":"San Vicente","oldName":"","subMunicipalityCode":false,"cityCode":false,"municipalityCode":"086402000","districtCode":false,"provinceCode":"086400000","regionCode":"080000000","islandGroupCode":"visayas","psgc10DigitCode":"0806402029"},{"code":"086402030","name":"Santa Cruz","oldName":"","subMunicipalityCode":false,"cityCode":false,"municipalityCode":"086402000","districtCode":false,"provinceCode":"086400000","regionCode":"080000000","islandGroupCode":"visayas","psgc10DigitCode":"0806402030"},{"code":"086402031","name":"Taa","oldName":"","subMunicipalityCode":false,"cityCode":false,"municipalityCode":"086402000","districtCode":false,"provinceCode":"086400000","regionCode":"080000000","islandGroupCode":"visayas","psgc10DigitCode":"0806402031"},{"code":"086402032","name":"Talisay","oldName":"","subMunicipalityCode":false,"cityCode":false,"municipalityCode":"086402000","districtCode":false,"provinceCode":"086400000","regionCode":"080000000","islandGroupCode":"visayas","psgc10DigitCode":"0806402032"},{"code":"086402033","name":"Taytagan","oldName":"","subMunicipalityCode":false,"cityCode":false,"municipalityCode":"086402000","districtCode":false,"provinceCode":"086400000","regionCode":"080000000","islandGroupCode":"visayas","psgc10DigitCode":"0806402033"},{"code":"086402034","name":"Tuburan","oldName":"","subMunicipalityCode":false,"cityCode":false,"municipalityCode":"086402000","districtCode":false,"provinceCode":"086400000","regionCode":"080000000","islandGroupCode":"visayas","psgc10DigitCode":"0806402034"},{"code":"086402035","name":"Union","oldName":"","subMunicipalityCode":false,"cityCode":false,"municipalityCode":"086402000","districtCode":false,"provinceCode":"086400000","regionCode":"080000000","islandGroupCode":"visayas","psgc10DigitCode":"0806402035"},{"code":"086402036","name":"Olisihan","oldName":"","subMunicipalityCode":false,"cityCode":false,"municipalityCode":"086402000","districtCode":false,"provinceCode":"086400000","regionCode":"080000000","islandGroupCode":"visayas","psgc10DigitCode":"0806402036"},{"code":"086402037","name":"Anahao","oldName":"","subMunicipalityCode":false,"cityCode":false,"municipalityCode":"086402000","districtCode":false,"provinceCode":"086400000","regionCode":"080000000","islandGroupCode":"visayas","psgc10DigitCode":"0806402037"},{"code":"086402038","name":"Pong-on","oldName":"","subMunicipalityCode":false,"cityCode":false,"municipalityCode":"086402000","districtCode":false,"provinceCode":"086400000","regionCode":"080000000","islandGroupCode":"visayas","psgc10DigitCode":"0806402038"},{"code":"086402039","name":"San Ramon","oldName":"","subMunicipalityCode":false,"cityCode":false,"municipalityCode":"086402000","districtCode":false,"provinceCode":"086400000","regionCode":"080000000","islandGroupCode":"visayas","psgc10DigitCode":"0806402039"},{"code":"086402040","name":"Santo Niño","oldName":"","subMunicipalityCode":false,"cityCode":false,"municipalityCode":"086402000","districtCode":false,"provinceCode":"086400000","regionCode":"080000000","islandGroupCode":"visayas","psgc10DigitCode":"0806402040"}]