[{"code":"051607001","name":"Apuao","oldName":"","subMunicipalityCode":false,"cityCode":false,"municipalityCode":"051607000","districtCode":false,"provinceCode":"051600000","regionCode":"050000000","islandGroupCode":"luzon","psgc10DigitCode":"0501607001"},{"code":"051607002","name":"Barangay I (Pob.)","oldName":"","subMunicipalityCode":false,"cityCode":false,"municipalityCode":"051607000","districtCode":false,"provinceCode":"051600000","regionCode":"050000000","islandGroupCode":"luzon","psgc10DigitCode":"0501607002"},{"code":"051607003","name":"Barangay II (Pob.)","oldName":"","subMunicipalityCode":false,"cityCode":false,"municipalityCode":"051607000","districtCode":false,"provinceCode":"051600000","regionCode":"050000000","islandGroupCode":"luzon","psgc10DigitCode":"0501607003"},{"code":"051607004","name":"Barangay III (Pob.)","oldName":"","subMunicipalityCode":false,"cityCode":false,"municipalityCode":"051607000","districtCode":false,"provinceCode":"051600000","regionCode":"050000000","islandGroupCode":"luzon","psgc10DigitCode":"0501607004"},{"code":"051607005","name":"Barangay IV (Pob.)","oldName":"","subMunicipalityCode":false,"cityCode":false,"municipalityCode":"051607000","districtCode":false,"provinceCode":"051600000","regionCode":"050000000","islandGroupCode":"luzon","psgc10DigitCode":"0501607005"},{"code":"051607006","name":"Barangay V (Pob.)","oldName":"","subMunicipalityCode":false,"cityCode":false,"municipalityCode":"051607000","districtCode":false,"provinceCode":"051600000","regionCode":"050000000","islandGroupCode":"luzon","psgc10DigitCode":"0501607006"},{"code":"051607007","name":"Barangay VI (Pob.)","oldName":"","subMunicipalityCode":false,"cityCode":false,"municipalityCode":"051607000","districtCode":false,"provinceCode":"051600000","regionCode":"050000000","islandGroupCode":"luzon","psgc10DigitCode":"0501607007"},{"code":"051607008","name":"Barangay VII (Pob.)","oldName":"","subMunicipalityCode":false,"cityCode":false,"municipalityCode":"051607000","districtCode":false,"provinceCode":"051600000","regionCode":"050000000","islandGroupCode":"luzon","psgc10DigitCode":"0501607008"},{"code":"051607009","name":"Caringo","oldName":"","subMunicipalityCode":false,"cityCode":false,"municipalityCode":"051607000","districtCode":false,"provinceCode":"051600000","regionCode":"050000000","islandGroupCode":"luzon","psgc10DigitCode":"0501607009"},{"code":"051607010","name":"Catandunganon","oldName":"","subMunicipalityCode":false,"cityCode":false,"municipalityCode":"051607000","districtCode":false,"provinceCode":"051600000","regionCode":"050000000","islandGroupCode":"luzon","psgc10DigitCode":"0501607010"},{"code":"051607011","name":"Cayucyucan","oldName":"","subMunicipalityCode":false,"cityCode":false,"municipalityCode":"051607000","districtCode":false,"provinceCode":"051600000","regionCode":"050000000","islandGroupCode":"luzon","psgc10DigitCode":"0501607011"},{"code":"051607012","name":"Colasi","oldName":"","subMunicipalityCode":false,"cityCode":false,"municipalityCode":"051607000","districtCode":false,"provinceCode":"051600000","regionCode":"050000000","islandGroupCode":"luzon","psgc10DigitCode":"0501607012"},{"code":"051607013","name":"Del Rosario","oldName":"Tagongtong","subMunicipalityCode":false,"cityCode":false,"municipalityCode":"051607000","districtCode":false,"provinceCode":"051600000","regionCode":"050000000","islandGroupCode":"luzon","psgc10DigitCode":"0501607013"},{"code":"051607014","name":"Gaboc","oldName":"","subMunicipalityCode":false,"cityCode":false,"municipalityCode":"051607000","districtCode":false,"provinceCode":"051600000","regionCode":"050000000","islandGroupCode":"luzon","psgc10DigitCode":"0501607014"},{"code":"051607015","name":"Hamoraon","oldName":"","subMunicipalityCode":false,"cityCode":false,"municipalityCode":"051607000","districtCode":false,"provinceCode":"051600000","regionCode":"050000000","islandGroupCode":"luzon","psgc10DigitCode":"0501607015"},{"code":"051607016","name":"Hinipaan","oldName":"","subMunicipalityCode":false,"cityCode":false,"municipalityCode":"051607000","districtCode":false,"provinceCode":"051600000","regionCode":"050000000","islandGroupCode":"luzon","psgc10DigitCode":"0501607016"},{"code":"051607017","name":"Lalawigan","oldName":"","subMunicipalityCode":false,"cityCode":false,"municipalityCode":"051607000","districtCode":false,"provinceCode":"051600000","regionCode":"050000000","islandGroupCode":"luzon","psgc10DigitCode":"0501607017"},{"code":"051607018","name":"Lanot","oldName":"","subMunicipalityCode":false,"cityCode":false,"municipalityCode":"051607000","districtCode":false,"provinceCode":"051600000","regionCode":"050000000","islandGroupCode":"luzon","psgc10DigitCode":"0501607018"},{"code":"051607019","name":"Mambungalon","oldName":"","subMunicipalityCode":false,"cityCode":false,"municipalityCode":"051607000","districtCode":false,"provinceCode":"051600000","regionCode":"050000000","islandGroupCode":"luzon","psgc10DigitCode":"0501607019"},{"code":"051607020","name":"Manguisoc","oldName":"","subMunicipalityCode":false,"cityCode":false,"municipalityCode":"051607000","districtCode":false,"provinceCode":"051600000","regionCode":"050000000","islandGroupCode":"luzon","psgc10DigitCode":"0501607020"},{"code":"051607021","name":"Masalongsalong","oldName":"","subMunicipalityCode":false,"cityCode":false,"municipalityCode":"051607000","districtCode":false,"provinceCode":"051600000","regionCode":"050000000","islandGroupCode":"luzon","psgc10DigitCode":"0501607021"},{"code":"051607022","name":"Matoogtoog","oldName":"","subMunicipalityCode":false,"cityCode":false,"municipalityCode":"051607000","districtCode":false,"provinceCode":"051600000","regionCode":"050000000","islandGroupCode":"luzon","psgc10DigitCode":"0501607022"},{"code":"051607023","name":"Pambuhan","oldName":"","subMunicipalityCode":false,"cityCode":false,"municipalityCode":"051607000","districtCode":false,"provinceCode":"051600000","regionCode":"050000000","islandGroupCode":"luzon","psgc10DigitCode":"0501607023"},{"code":"051607024","name":"Quinapaguian","oldName":"","subMunicipalityCode":false,"cityCode":false,"municipalityCode":"051607000","districtCode":false,"provinceCode":"051600000","regionCode":"050000000","islandGroupCode":"luzon","psgc10DigitCode":"0501607024"},{"code":"051607025","name":"San Roque","oldName":"","subMunicipalityCode":false,"cityCode":false,"municipalityCode":"051607000","districtCode":false,"provinceCode":"051600000","regionCode":"050000000","islandGroupCode":"luzon","psgc10DigitCode":"0501607025"},{"code":"051607026","name":"Tarum","oldName":"","subMunicipalityCode":false,"cityCode":false,"municipalityCode":"051607000","districtCode":false,"provinceCode":"051600000","regionCode":"050000000","islandGroupCode":"luzon","psgc10DigitCode":"0501607026"}]