[{"code":"083733001","name":"Balagtas","oldName":"","subMunicipalityCode":false,"cityCode":false,"municipalityCode":"083733000","districtCode":false,"provinceCode":"083700000","regionCode":"080000000","islandGroupCode":"visayas","psgc10DigitCode":"0803733001"},{"code":"083733002","name":"Bulak","oldName":"","subMunicipalityCode":false,"cityCode":false,"municipalityCode":"083733000","districtCode":false,"provinceCode":"083700000","regionCode":"080000000","islandGroupCode":"visayas","psgc10DigitCode":"0803733002"},{"code":"083733003","name":"Cambadbad","oldName":"","subMunicipalityCode":false,"cityCode":false,"municipalityCode":"083733000","districtCode":false,"provinceCode":"083700000","regionCode":"080000000","islandGroupCode":"visayas","psgc10DigitCode":"0803733003"},{"code":"083733004","name":"Candelaria","oldName":"","subMunicipalityCode":false,"cityCode":false,"municipalityCode":"083733000","districtCode":false,"provinceCode":"083700000","regionCode":"080000000","islandGroupCode":"visayas","psgc10DigitCode":"0803733004"},{"code":"083733005","name":"Cansoso","oldName":"","subMunicipalityCode":false,"cityCode":false,"municipalityCode":"083733000","districtCode":false,"provinceCode":"083700000","regionCode":"080000000","islandGroupCode":"visayas","psgc10DigitCode":"0803733005"},{"code":"083733006","name":"Mansahaon","oldName":"","subMunicipalityCode":false,"cityCode":false,"municipalityCode":"083733000","districtCode":false,"provinceCode":"083700000","regionCode":"080000000","islandGroupCode":"visayas","psgc10DigitCode":"0803733006"},{"code":"083733007","name":"Masaba","oldName":"","subMunicipalityCode":false,"cityCode":false,"municipalityCode":"083733000","districtCode":false,"provinceCode":"083700000","regionCode":"080000000","islandGroupCode":"visayas","psgc10DigitCode":"0803733007"},{"code":"083733008","name":"Naulayan","oldName":"","subMunicipalityCode":false,"cityCode":false,"municipalityCode":"083733000","districtCode":false,"provinceCode":"083700000","regionCode":"080000000","islandGroupCode":"visayas","psgc10DigitCode":"0803733008"},{"code":"083733009","name":"Bonoy (Pob.)","oldName":"","subMunicipalityCode":false,"cityCode":false,"municipalityCode":"083733000","districtCode":false,"provinceCode":"083700000","regionCode":"080000000","islandGroupCode":"visayas","psgc10DigitCode":"0803733009"},{"code":"083733010","name":"Mansalip (Pob.)","oldName":"","subMunicipalityCode":false,"cityCode":false,"municipalityCode":"083733000","districtCode":false,"provinceCode":"083700000","regionCode":"080000000","islandGroupCode":"visayas","psgc10DigitCode":"0803733010"},{"code":"083733011","name":"Riverside (Pob.)","oldName":"","subMunicipalityCode":false,"cityCode":false,"municipalityCode":"083733000","districtCode":false,"provinceCode":"083700000","regionCode":"080000000","islandGroupCode":"visayas","psgc10DigitCode":"0803733011"},{"code":"083733012","name":"Talisay (Pob.)","oldName":"","subMunicipalityCode":false,"cityCode":false,"municipalityCode":"083733000","districtCode":false,"provinceCode":"083700000","regionCode":"080000000","islandGroupCode":"visayas","psgc10DigitCode":"0803733012"},{"code":"083733013","name":"San Dionisio","oldName":"","subMunicipalityCode":false,"cityCode":false,"municipalityCode":"083733000","districtCode":false,"provinceCode":"083700000","regionCode":"080000000","islandGroupCode":"visayas","psgc10DigitCode":"0803733013"},{"code":"083733014","name":"San Marcelino","oldName":"","subMunicipalityCode":false,"cityCode":false,"municipalityCode":"083733000","districtCode":false,"provinceCode":"083700000","regionCode":"080000000","islandGroupCode":"visayas","psgc10DigitCode":"0803733014"},{"code":"083733015","name":"San Sebastian","oldName":"","subMunicipalityCode":false,"cityCode":false,"municipalityCode":"083733000","districtCode":false,"provinceCode":"083700000","regionCode":"080000000","islandGroupCode":"visayas","psgc10DigitCode":"0803733015"},{"code":"083733016","name":"San Vicente","oldName":"","subMunicipalityCode":false,"cityCode":false,"municipalityCode":"083733000","districtCode":false,"provinceCode":"083700000","regionCode":"080000000","islandGroupCode":"visayas","psgc10DigitCode":"0803733016"},{"code":"083733017","name":"Santa Rosa","oldName":"","subMunicipalityCode":false,"cityCode":false,"municipalityCode":"083733000","districtCode":false,"provinceCode":"083700000","regionCode":"080000000","islandGroupCode":"visayas","psgc10DigitCode":"0803733017"},{"code":"083733018","name":"Santo Rosario","oldName":"","subMunicipalityCode":false,"cityCode":false,"municipalityCode":"083733000","districtCode":false,"provinceCode":"083700000","regionCode":"080000000","islandGroupCode":"visayas","psgc10DigitCode":"0803733018"},{"code":"083733019","name":"Imelda","oldName":"","subMunicipalityCode":false,"cityCode":false,"municipalityCode":"083733000","districtCode":false,"provinceCode":"083700000","regionCode":"080000000","islandGroupCode":"visayas","psgc10DigitCode":"0803733019"},{"code":"083733020","name":"Malazarte","oldName":"","subMunicipalityCode":false,"cityCode":false,"municipalityCode":"083733000","districtCode":false,"provinceCode":"083700000","regionCode":"080000000","islandGroupCode":"visayas","psgc10DigitCode":"0803733020"},{"code":"083733021","name":"San Guillermo","oldName":"","subMunicipalityCode":false,"cityCode":false,"municipalityCode":"083733000","districtCode":false,"provinceCode":"083700000","regionCode":"080000000","islandGroupCode":"visayas","psgc10DigitCode":"0803733021"}]