[{"code":"087802001","name":"Bato","oldName":"","subMunicipalityCode":false,"cityCode":false,"municipalityCode":"087802000","districtCode":false,"provinceCode":"087800000","regionCode":"080000000","islandGroupCode":"visayas","psgc10DigitCode":"0807802001"},{"code":"087802002","name":"Burabod","oldName":"","subMunicipalityCode":false,"cityCode":false,"municipalityCode":"087802000","districtCode":false,"provinceCode":"087800000","regionCode":"080000000","islandGroupCode":"visayas","psgc10DigitCode":"0807802002"},{"code":"087802003","name":"Busali","oldName":"","subMunicipalityCode":false,"cityCode":false,"municipalityCode":"087802000","districtCode":false,"provinceCode":"087800000","regionCode":"080000000","islandGroupCode":"visayas","psgc10DigitCode":"0807802003"},{"code":"087802004","name":"Hugpa","oldName":"","subMunicipalityCode":false,"cityCode":false,"municipalityCode":"087802000","districtCode":false,"provinceCode":"087800000","regionCode":"080000000","islandGroupCode":"visayas","psgc10DigitCode":"0807802004"},{"code":"087802005","name":"Julita","oldName":"","subMunicipalityCode":false,"cityCode":false,"municipalityCode":"087802000","districtCode":false,"provinceCode":"087800000","regionCode":"080000000","islandGroupCode":"visayas","psgc10DigitCode":"0807802005"},{"code":"087802006","name":"Canila","oldName":"","subMunicipalityCode":false,"cityCode":false,"municipalityCode":"087802000","districtCode":false,"provinceCode":"087800000","regionCode":"080000000","islandGroupCode":"visayas","psgc10DigitCode":"0807802006"},{"code":"087802007","name":"Pinangumhan","oldName":"","subMunicipalityCode":false,"cityCode":false,"municipalityCode":"087802000","districtCode":false,"provinceCode":"087800000","regionCode":"080000000","islandGroupCode":"visayas","psgc10DigitCode":"0807802007"},{"code":"087802008","name":"San Isidro (Pob.)","oldName":"","subMunicipalityCode":false,"cityCode":false,"municipalityCode":"087802000","districtCode":false,"provinceCode":"087800000","regionCode":"080000000","islandGroupCode":"visayas","psgc10DigitCode":"0807802008"},{"code":"087802009","name":"San Roque (Pob.)","oldName":"","subMunicipalityCode":false,"cityCode":false,"municipalityCode":"087802000","districtCode":false,"provinceCode":"087800000","regionCode":"080000000","islandGroupCode":"visayas","psgc10DigitCode":"0807802009"},{"code":"087802010","name":"Sanggalang","oldName":"","subMunicipalityCode":false,"cityCode":false,"municipalityCode":"087802000","districtCode":false,"provinceCode":"087800000","regionCode":"080000000","islandGroupCode":"visayas","psgc10DigitCode":"0807802010"},{"code":"087802011","name":"Villa Enage","oldName":"Baras","subMunicipalityCode":false,"cityCode":false,"municipalityCode":"087802000","districtCode":false,"provinceCode":"087800000","regionCode":"080000000","islandGroupCode":"visayas","psgc10DigitCode":"0807802011"}]