[{"code":"054112001","name":"Bacolod","oldName":"","subMunicipalityCode":false,"cityCode":false,"municipalityCode":"054112000","districtCode":false,"provinceCode":"054100000","regionCode":"050000000","islandGroupCode":"luzon","psgc10DigitCode":"0504112001"},{"code":"054112002","name":"Bangad","oldName":"","subMunicipalityCode":false,"cityCode":false,"municipalityCode":"054112000","districtCode":false,"provinceCode":"054100000","regionCode":"050000000","islandGroupCode":"luzon","psgc10DigitCode":"0504112002"},{"code":"054112003","name":"Bara","oldName":"","subMunicipalityCode":false,"cityCode":false,"municipalityCode":"054112000","districtCode":false,"provinceCode":"054100000","regionCode":"050000000","islandGroupCode":"luzon","psgc10DigitCode":"0504112003"},{"code":"054112004","name":"Bonbon","oldName":"","subMunicipalityCode":false,"cityCode":false,"municipalityCode":"054112000","districtCode":false,"provinceCode":"054100000","regionCode":"050000000","islandGroupCode":"luzon","psgc10DigitCode":"0504112004"},{"code":"054112005","name":"Calasuche","oldName":"","subMunicipalityCode":false,"cityCode":false,"municipalityCode":"054112000","districtCode":false,"provinceCode":"054100000","regionCode":"050000000","islandGroupCode":"luzon","psgc10DigitCode":"0504112005"},{"code":"054112006","name":"Calumpang","oldName":"Taisan","subMunicipalityCode":false,"cityCode":false,"municipalityCode":"054112000","districtCode":false,"provinceCode":"054100000","regionCode":"050000000","islandGroupCode":"luzon","psgc10DigitCode":"0504112006"},{"code":"054112007","name":"Capaculan","oldName":"","subMunicipalityCode":false,"cityCode":false,"municipalityCode":"054112000","districtCode":false,"provinceCode":"054100000","regionCode":"050000000","islandGroupCode":"luzon","psgc10DigitCode":"0504112007"},{"code":"054112008","name":"Cayabon","oldName":"","subMunicipalityCode":false,"cityCode":false,"municipalityCode":"054112000","districtCode":false,"provinceCode":"054100000","regionCode":"050000000","islandGroupCode":"luzon","psgc10DigitCode":"0504112008"},{"code":"054112009","name":"Guinluthangan","oldName":"","subMunicipalityCode":false,"cityCode":false,"municipalityCode":"054112000","districtCode":false,"provinceCode":"054100000","regionCode":"050000000","islandGroupCode":"luzon","psgc10DigitCode":"0504112009"},{"code":"054112010","name":"Jamorawon","oldName":"","subMunicipalityCode":false,"cityCode":false,"municipalityCode":"054112000","districtCode":false,"provinceCode":"054100000","regionCode":"050000000","islandGroupCode":"luzon","psgc10DigitCode":"0504112010"},{"code":"054112011","name":"Magsalangi","oldName":"","subMunicipalityCode":false,"cityCode":false,"municipalityCode":"054112000","districtCode":false,"provinceCode":"054100000","regionCode":"050000000","islandGroupCode":"luzon","psgc10DigitCode":"0504112011"},{"code":"054112012","name":"Matagbac","oldName":"","subMunicipalityCode":false,"cityCode":false,"municipalityCode":"054112000","districtCode":false,"provinceCode":"054100000","regionCode":"050000000","islandGroupCode":"luzon","psgc10DigitCode":"0504112012"},{"code":"054112013","name":"Matanglad","oldName":"","subMunicipalityCode":false,"cityCode":false,"municipalityCode":"054112000","districtCode":false,"provinceCode":"054100000","regionCode":"050000000","islandGroupCode":"luzon","psgc10DigitCode":"0504112013"},{"code":"054112014","name":"Matiporon","oldName":"","subMunicipalityCode":false,"cityCode":false,"municipalityCode":"054112000","districtCode":false,"provinceCode":"054100000","regionCode":"050000000","islandGroupCode":"luzon","psgc10DigitCode":"0504112014"},{"code":"054112015","name":"Moises R. Espinosa","oldName":"","subMunicipalityCode":false,"cityCode":false,"municipalityCode":"054112000","districtCode":false,"provinceCode":"054100000","regionCode":"050000000","islandGroupCode":"luzon","psgc10DigitCode":"0504112015"},{"code":"054112016","name":"Narangasan","oldName":"","subMunicipalityCode":false,"cityCode":false,"municipalityCode":"054112000","districtCode":false,"provinceCode":"054100000","regionCode":"050000000","islandGroupCode":"luzon","psgc10DigitCode":"0504112016"},{"code":"054112018","name":"Pamangpangon","oldName":"","subMunicipalityCode":false,"cityCode":false,"municipalityCode":"054112000","districtCode":false,"provinceCode":"054100000","regionCode":"050000000","islandGroupCode":"luzon","psgc10DigitCode":"0504112018"},{"code":"054112019","name":"Poblacion East","oldName":"","subMunicipalityCode":false,"cityCode":false,"municipalityCode":"054112000","districtCode":false,"provinceCode":"054100000","regionCode":"050000000","islandGroupCode":"luzon","psgc10DigitCode":"0504112019"},{"code":"054112020","name":"Poblacion West","oldName":"","subMunicipalityCode":false,"cityCode":false,"municipalityCode":"054112000","districtCode":false,"provinceCode":"054100000","regionCode":"050000000","islandGroupCode":"luzon","psgc10DigitCode":"0504112020"},{"code":"054112021","name":"Paraiso","oldName":"Potot","subMunicipalityCode":false,"cityCode":false,"municipalityCode":"054112000","districtCode":false,"provinceCode":"054100000","regionCode":"050000000","islandGroupCode":"luzon","psgc10DigitCode":"0504112021"},{"code":"054112022","name":"San Antonio","oldName":"","subMunicipalityCode":false,"cityCode":false,"municipalityCode":"054112000","districtCode":false,"provinceCode":"054100000","regionCode":"050000000","islandGroupCode":"luzon","psgc10DigitCode":"0504112022"},{"code":"054112023","name":"San Carlos","oldName":"","subMunicipalityCode":false,"cityCode":false,"municipalityCode":"054112000","districtCode":false,"provinceCode":"054100000","regionCode":"050000000","islandGroupCode":"luzon","psgc10DigitCode":"0504112023"},{"code":"054112024","name":"Sawmill","oldName":"","subMunicipalityCode":false,"cityCode":false,"municipalityCode":"054112000","districtCode":false,"provinceCode":"054100000","regionCode":"050000000","islandGroupCode":"luzon","psgc10DigitCode":"0504112024"},{"code":"054112025","name":"Tagbon","oldName":"","subMunicipalityCode":false,"cityCode":false,"municipalityCode":"054112000","districtCode":false,"provinceCode":"054100000","regionCode":"050000000","islandGroupCode":"luzon","psgc10DigitCode":"0504112025"},{"code":"054112026","name":"Tawad","oldName":"","subMunicipalityCode":false,"cityCode":false,"municipalityCode":"054112000","districtCode":false,"provinceCode":"054100000","regionCode":"050000000","islandGroupCode":"luzon","psgc10DigitCode":"0504112026"},{"code":"054112027","name":"Tigbao","oldName":"","subMunicipalityCode":false,"cityCode":false,"municipalityCode":"054112000","districtCode":false,"provinceCode":"054100000","regionCode":"050000000","islandGroupCode":"luzon","psgc10DigitCode":"0504112027"},{"code":"054112028","name":"Tinaclipan","oldName":"Bato","subMunicipalityCode":false,"cityCode":false,"municipalityCode":"054112000","districtCode":false,"provinceCode":"054100000","regionCode":"050000000","islandGroupCode":"luzon","psgc10DigitCode":"0504112028"}]