[{"code":"043413001","name":"Bagong Silang","oldName":"","subMunicipalityCode":false,"cityCode":false,"municipalityCode":"043413000","districtCode":false,"provinceCode":"043400000","regionCode":"040000000","islandGroupCode":"luzon","psgc10DigitCode":"0403413001"},{"code":"043413002","name":"Balimbingan (Pob.)","oldName":"","subMunicipalityCode":false,"cityCode":false,"municipalityCode":"043413000","districtCode":false,"provinceCode":"043400000","regionCode":"040000000","islandGroupCode":"luzon","psgc10DigitCode":"0403413002"},{"code":"043413003","name":"Balubad","oldName":"","subMunicipalityCode":false,"cityCode":false,"municipalityCode":"043413000","districtCode":false,"provinceCode":"043400000","regionCode":"040000000","islandGroupCode":"luzon","psgc10DigitCode":"0403413003"},{"code":"043413004","name":"Caliraya","oldName":"","subMunicipalityCode":false,"cityCode":false,"municipalityCode":"043413000","districtCode":false,"provinceCode":"043400000","regionCode":"040000000","islandGroupCode":"luzon","psgc10DigitCode":"0403413004"},{"code":"043413005","name":"Concepcion","oldName":"","subMunicipalityCode":false,"cityCode":false,"municipalityCode":"043413000","districtCode":false,"provinceCode":"043400000","regionCode":"040000000","islandGroupCode":"luzon","psgc10DigitCode":"0403413005"},{"code":"043413006","name":"Lewin","oldName":"","subMunicipalityCode":false,"cityCode":false,"municipalityCode":"043413000","districtCode":false,"provinceCode":"043400000","regionCode":"040000000","islandGroupCode":"luzon","psgc10DigitCode":"0403413006"},{"code":"043413007","name":"Maracta (Pob.)","oldName":"","subMunicipalityCode":false,"cityCode":false,"municipalityCode":"043413000","districtCode":false,"provinceCode":"043400000","regionCode":"040000000","islandGroupCode":"luzon","psgc10DigitCode":"0403413007"},{"code":"043413008","name":"Maytalang I","oldName":"","subMunicipalityCode":false,"cityCode":false,"municipalityCode":"043413000","districtCode":false,"provinceCode":"043400000","regionCode":"040000000","islandGroupCode":"luzon","psgc10DigitCode":"0403413008"},{"code":"043413009","name":"Maytalang II","oldName":"","subMunicipalityCode":false,"cityCode":false,"municipalityCode":"043413000","districtCode":false,"provinceCode":"043400000","regionCode":"040000000","islandGroupCode":"luzon","psgc10DigitCode":"0403413009"},{"code":"043413010","name":"Primera Parang (Pob.)","oldName":"","subMunicipalityCode":false,"cityCode":false,"municipalityCode":"043413000","districtCode":false,"provinceCode":"043400000","regionCode":"040000000","islandGroupCode":"luzon","psgc10DigitCode":"0403413010"},{"code":"043413011","name":"Primera Pulo (Pob.)","oldName":"","subMunicipalityCode":false,"cityCode":false,"municipalityCode":"043413000","districtCode":false,"provinceCode":"043400000","regionCode":"040000000","islandGroupCode":"luzon","psgc10DigitCode":"0403413011"},{"code":"043413012","name":"Salac (Pob.)","oldName":"","subMunicipalityCode":false,"cityCode":false,"municipalityCode":"043413000","districtCode":false,"provinceCode":"043400000","regionCode":"040000000","islandGroupCode":"luzon","psgc10DigitCode":"0403413012"},{"code":"043413013","name":"Segunda Parang (Pob.)","oldName":"","subMunicipalityCode":false,"cityCode":false,"municipalityCode":"043413000","districtCode":false,"provinceCode":"043400000","regionCode":"040000000","islandGroupCode":"luzon","psgc10DigitCode":"0403413013"},{"code":"043413014","name":"Segunda Pulo (Pob.)","oldName":"","subMunicipalityCode":false,"cityCode":false,"municipalityCode":"043413000","districtCode":false,"provinceCode":"043400000","regionCode":"040000000","islandGroupCode":"luzon","psgc10DigitCode":"0403413014"},{"code":"043413015","name":"Santo Niño (Pob.)","oldName":"","subMunicipalityCode":false,"cityCode":false,"municipalityCode":"043413000","districtCode":false,"provinceCode":"043400000","regionCode":"040000000","islandGroupCode":"luzon","psgc10DigitCode":"0403413015"},{"code":"043413016","name":"Wawa","oldName":"","subMunicipalityCode":false,"cityCode":false,"municipalityCode":"043413000","districtCode":false,"provinceCode":"043400000","regionCode":"040000000","islandGroupCode":"luzon","psgc10DigitCode":"0403413016"}]