[{"code":"072222001","name":"Ablayan","oldName":"","subMunicipalityCode":false,"cityCode":false,"municipalityCode":"072222000","districtCode":false,"provinceCode":"072200000","regionCode":"070000000","islandGroupCode":"visayas","psgc10DigitCode":"0702222001"},{"code":"072222002","name":"Babayongan","oldName":"","subMunicipalityCode":false,"cityCode":false,"municipalityCode":"072222000","districtCode":false,"provinceCode":"072200000","regionCode":"070000000","islandGroupCode":"visayas","psgc10DigitCode":"0702222002"},{"code":"072222003","name":"Balud","oldName":"","subMunicipalityCode":false,"cityCode":false,"municipalityCode":"072222000","districtCode":false,"provinceCode":"072200000","regionCode":"070000000","islandGroupCode":"visayas","psgc10DigitCode":"0702222003"},{"code":"072222004","name":"Banhigan","oldName":"","subMunicipalityCode":false,"cityCode":false,"municipalityCode":"072222000","districtCode":false,"provinceCode":"072200000","regionCode":"070000000","islandGroupCode":"visayas","psgc10DigitCode":"0702222004"},{"code":"072222005","name":"Bulak","oldName":"","subMunicipalityCode":false,"cityCode":false,"municipalityCode":"072222000","districtCode":false,"provinceCode":"072200000","regionCode":"070000000","islandGroupCode":"visayas","psgc10DigitCode":"0702222005"},{"code":"072222006","name":"Caliongan","oldName":"","subMunicipalityCode":false,"cityCode":false,"municipalityCode":"072222000","districtCode":false,"provinceCode":"072200000","regionCode":"070000000","islandGroupCode":"visayas","psgc10DigitCode":"0702222006"},{"code":"072222007","name":"Caleriohan","oldName":"","subMunicipalityCode":false,"cityCode":false,"municipalityCode":"072222000","districtCode":false,"provinceCode":"072200000","regionCode":"070000000","islandGroupCode":"visayas","psgc10DigitCode":"0702222007"},{"code":"072222008","name":"Casay","oldName":"","subMunicipalityCode":false,"cityCode":false,"municipalityCode":"072222000","districtCode":false,"provinceCode":"072200000","regionCode":"070000000","islandGroupCode":"visayas","psgc10DigitCode":"0702222008"},{"code":"072222009","name":"Catolohan","oldName":"","subMunicipalityCode":false,"cityCode":false,"municipalityCode":"072222000","districtCode":false,"provinceCode":"072200000","regionCode":"070000000","islandGroupCode":"visayas","psgc10DigitCode":"0702222009"},{"code":"072222010","name":"Cawayan","oldName":"","subMunicipalityCode":false,"cityCode":false,"municipalityCode":"072222000","districtCode":false,"provinceCode":"072200000","regionCode":"070000000","islandGroupCode":"visayas","psgc10DigitCode":"0702222010"},{"code":"072222011","name":"Consolacion","oldName":"","subMunicipalityCode":false,"cityCode":false,"municipalityCode":"072222000","districtCode":false,"provinceCode":"072200000","regionCode":"070000000","islandGroupCode":"visayas","psgc10DigitCode":"0702222011"},{"code":"072222012","name":"Coro","oldName":"","subMunicipalityCode":false,"cityCode":false,"municipalityCode":"072222000","districtCode":false,"provinceCode":"072200000","regionCode":"070000000","islandGroupCode":"visayas","psgc10DigitCode":"0702222012"},{"code":"072222013","name":"Dugyan","oldName":"","subMunicipalityCode":false,"cityCode":false,"municipalityCode":"072222000","districtCode":false,"provinceCode":"072200000","regionCode":"070000000","islandGroupCode":"visayas","psgc10DigitCode":"0702222013"},{"code":"072222014","name":"Dumalan","oldName":"","subMunicipalityCode":false,"cityCode":false,"municipalityCode":"072222000","districtCode":false,"provinceCode":"072200000","regionCode":"070000000","islandGroupCode":"visayas","psgc10DigitCode":"0702222014"},{"code":"072222015","name":"Jolomaynon","oldName":"","subMunicipalityCode":false,"cityCode":false,"municipalityCode":"072222000","districtCode":false,"provinceCode":"072200000","regionCode":"070000000","islandGroupCode":"visayas","psgc10DigitCode":"0702222015"},{"code":"072222016","name":"Lanao","oldName":"","subMunicipalityCode":false,"cityCode":false,"municipalityCode":"072222000","districtCode":false,"provinceCode":"072200000","regionCode":"070000000","islandGroupCode":"visayas","psgc10DigitCode":"0702222016"},{"code":"072222017","name":"Langkas","oldName":"","subMunicipalityCode":false,"cityCode":false,"municipalityCode":"072222000","districtCode":false,"provinceCode":"072200000","regionCode":"070000000","islandGroupCode":"visayas","psgc10DigitCode":"0702222017"},{"code":"072222018","name":"Lumbang","oldName":"","subMunicipalityCode":false,"cityCode":false,"municipalityCode":"072222000","districtCode":false,"provinceCode":"072200000","regionCode":"070000000","islandGroupCode":"visayas","psgc10DigitCode":"0702222018"},{"code":"072222019","name":"Malones","oldName":"","subMunicipalityCode":false,"cityCode":false,"municipalityCode":"072222000","districtCode":false,"provinceCode":"072200000","regionCode":"070000000","islandGroupCode":"visayas","psgc10DigitCode":"0702222019"},{"code":"072222020","name":"Maloray","oldName":"","subMunicipalityCode":false,"cityCode":false,"municipalityCode":"072222000","districtCode":false,"provinceCode":"072200000","regionCode":"070000000","islandGroupCode":"visayas","psgc10DigitCode":"0702222020"},{"code":"072222021","name":"Mananggal","oldName":"","subMunicipalityCode":false,"cityCode":false,"municipalityCode":"072222000","districtCode":false,"provinceCode":"072200000","regionCode":"070000000","islandGroupCode":"visayas","psgc10DigitCode":"0702222021"},{"code":"072222023","name":"Manlapay","oldName":"","subMunicipalityCode":false,"cityCode":false,"municipalityCode":"072222000","districtCode":false,"provinceCode":"072200000","regionCode":"070000000","islandGroupCode":"visayas","psgc10DigitCode":"0702222023"},{"code":"072222024","name":"Mantalongon","oldName":"","subMunicipalityCode":false,"cityCode":false,"municipalityCode":"072222000","districtCode":false,"provinceCode":"072200000","regionCode":"070000000","islandGroupCode":"visayas","psgc10DigitCode":"0702222024"},{"code":"072222025","name":"Nalhub","oldName":"","subMunicipalityCode":false,"cityCode":false,"municipalityCode":"072222000","districtCode":false,"provinceCode":"072200000","regionCode":"070000000","islandGroupCode":"visayas","psgc10DigitCode":"0702222025"},{"code":"072222026","name":"Obo","oldName":"","subMunicipalityCode":false,"cityCode":false,"municipalityCode":"072222000","districtCode":false,"provinceCode":"072200000","regionCode":"070000000","islandGroupCode":"visayas","psgc10DigitCode":"0702222026"},{"code":"072222027","name":"Obong","oldName":"","subMunicipalityCode":false,"cityCode":false,"municipalityCode":"072222000","districtCode":false,"provinceCode":"072200000","regionCode":"070000000","islandGroupCode":"visayas","psgc10DigitCode":"0702222027"},{"code":"072222028","name":"Panas","oldName":"","subMunicipalityCode":false,"cityCode":false,"municipalityCode":"072222000","districtCode":false,"provinceCode":"072200000","regionCode":"070000000","islandGroupCode":"visayas","psgc10DigitCode":"0702222028"},{"code":"072222029","name":"Poblacion","oldName":"","subMunicipalityCode":false,"cityCode":false,"municipalityCode":"072222000","districtCode":false,"provinceCode":"072200000","regionCode":"070000000","islandGroupCode":"visayas","psgc10DigitCode":"0702222029"},{"code":"072222030","name":"Sacsac","oldName":"","subMunicipalityCode":false,"cityCode":false,"municipalityCode":"072222000","districtCode":false,"provinceCode":"072200000","regionCode":"070000000","islandGroupCode":"visayas","psgc10DigitCode":"0702222030"},{"code":"072222031","name":"Tapun","oldName":"","subMunicipalityCode":false,"cityCode":false,"municipalityCode":"072222000","districtCode":false,"provinceCode":"072200000","regionCode":"070000000","islandGroupCode":"visayas","psgc10DigitCode":"0702222031"},{"code":"072222032","name":"Tuba","oldName":"","subMunicipalityCode":false,"cityCode":false,"municipalityCode":"072222000","districtCode":false,"provinceCode":"072200000","regionCode":"070000000","islandGroupCode":"visayas","psgc10DigitCode":"0702222032"},{"code":"072222033","name":"Salug","oldName":"","subMunicipalityCode":false,"cityCode":false,"municipalityCode":"072222000","districtCode":false,"provinceCode":"072200000","regionCode":"070000000","islandGroupCode":"visayas","psgc10DigitCode":"0702222033"},{"code":"072222034","name":"Tabon","oldName":"","subMunicipalityCode":false,"cityCode":false,"municipalityCode":"072222000","districtCode":false,"provinceCode":"072200000","regionCode":"070000000","islandGroupCode":"visayas","psgc10DigitCode":"0702222034"}]